src/__init__.py
wordwizard-0.1.0.dist-info/METADATA
wordwizard-0.1.0.dist-info/WHEEL
wordwizard-0.1.0.dist-info/top_level.txt
wordwizard-0.1.0.dist-info/RECORD
