Metadata-Version: 2.4
Name: wordwizard
Version: 0.1.0
Summary: A simple word processing and analysis tool
Home-page: https://github.com/eldareliyev/wordwizard
Author: Eldar Eliyev
License: MIT
Platform: any
Classifier: Programming Language :: Python :: 3
Classifier: License :: OSI Approved :: MIT License
Classifier: Operating System :: OS Independent
Requires-Python: >=3.8
